brain_games/__init__.py
brain_games/cli.py
brain_games/engine.py
brain_games/games/__init__.py
brain_games/games/brain_calc.py
brain_games/games/brain_even.py
brain_games/games/brain_gcd.py
brain_games/games/brain_prime.py
brain_games/games/brain_progression.py
brain_games/scripts/__init__.py
brain_games/scripts/brain_calc.py
brain_games/scripts/brain_even.py
brain_games/scripts/brain_games.py
brain_games/scripts/brain_gcd.py
brain_games/scripts/brain_prime.py
brain_games/scripts/brain_progression.py
artemy64_brain_games-0.1.0.dist-info/entry_points.txt
artemy64_brain_games-0.1.0.dist-info/WHEEL
artemy64_brain_games-0.1.0.dist-info/METADATA
artemy64_brain_games-0.1.0.dist-info/RECORD
