Metadata-Version: 2.1
Name: artemy64-brain-games
Version: 0.1.0
Summary: Brain Games Education Project
Home-page: https://github.com/ArtemyAndrienko/python-project-lvl1
License: MIT
Author: _artemy
Author-email: artemy.andrienko@gmail.com
Requires-Python: >=3.8,<4.0
Classifier: License :: OSI Approved :: MIT License
Classifier: Programming Language :: Python :: 3
Classifier: Programming Language :: Python :: 3.8
Classifier: Programming Language :: Python :: 3.9
Classifier: Topic :: Education
Requires-Dist: prompt (>=0.4.1,<0.5.0)
Project-URL: Repository, https://github.com/ArtemyAndrienko/python-project-lvl1
